devoutils/__init__.py
devoutils/__version__.py
devoutils/faker/__init__.py
devoutils/faker/generators/__init__.py
devoutils/faker/generators/base_fake_generator.py
devoutils/faker/generators/batch_fake_generator.py
devoutils/faker/generators/file_fake_generator.py
devoutils/faker/generators/realtime_fake_generator.py
devoutils/faker/generators/simulation_fake_generator.py
devoutils/faker/generators/syslog_fake_generator.py
devoutils/faker/generators/syslog_raw_fake_generator.py
devoutils/faker/generators/template_parser.py
devoutils/faker/providers/__init__.py
devoutils/faker/providers/file_data_source_provider.py
devoutils/faker/providers/numbers_provider.py
devoutils/faker/scripts/__init__.py
devoutils/faker/scripts/faker_cli.py
devoutils/faker/senders/__init__.py
devoutils/faker/senders/base_sender.py
devoutils/faker/senders/batch_sender.py
devoutils/faker/senders/file_sender.py
devoutils/faker/senders/syslog_raw_sender.py
devoutils/faker/senders/syslog_sender.py
devoutils/faker/senders/template_parser.py
devoutils/fileio/__init__.py
devoutils/fileio/file_reader.py
devoutils/fileio/file_sorted_join.py
devoutils/fileio/file_writer.py
devoutils/sorter/__init__.py
devoutils/sorter/cmp_compatible.py
devoutils/sorter/comparator.py
devoutils/sorter/file_sorted_join.py
devoutils/sorter/parser.py
devoutils/sorter/sorter.py
tests/__init__.py
tests/dataio/__init__.py
tests/dataio/fileio.py
tests/devo_faker/__init__.py
tests/devo_faker/template_parser.py
tests/sorter/__init__.py
tests/sorter/file_sorter.py
tests/sorter/memory_safe.py
devo_utils-3.0.7.dist-info/LICENSE
devo_utils-3.0.7.dist-info/METADATA
devo_utils-3.0.7.dist-info/WHEEL
devo_utils-3.0.7.dist-info/entry_points.txt
devo_utils-3.0.7.dist-info/top_level.txt
devo_utils-3.0.7.dist-info/RECORD
