Metadata-Version: 2.1
Name: devo-utils
Version: 3.0.7
Summary: Devo Utils for Python.
Home-page: https://github.com/DevoInc/python-utils
Author: Devo, Inc.
Author-email: support@devo.com
License: MIT
Platform: UNKNOWN
Classifier: Programming Language :: Python
Classifier: Development Status :: 5 - Production/Stable
Classifier: Intended Audience :: Developers
Classifier: Natural Language :: English
Classifier: License :: OSI Approved :: MIT License
Classifier: Operating System :: OS Independent
Classifier: Programming Language :: Python :: 3
Classifier: Programming Language :: Python :: 3.5
Classifier: Programming Language :: Python :: 3.6
Classifier: Programming Language :: Python :: 3.7
Classifier: Programming Language :: Python :: Implementation :: CPython
Classifier: Programming Language :: Python :: Implementation :: PyPy
Classifier: Topic :: Software Development :: Libraries :: Python Modules
Requires-Dist: devo-sdk (==3.4.2)
Requires-Dist: click (==7.1.1)
Requires-Dist: requests (==2.23.0)
Requires-Dist: PyYAML (==5.4.1)
Requires-Dist: Jinja2 (==2.11.3)
Requires-Dist: psutil (==5.7.0)
Requires-Dist: python-dateutil (==2.8.1)
Requires-Dist: Faker (==4.0.2)
Requires-Dist: pycron (==3.0.0)
